README.rst
setup.py
hic/__init__.py
hic/flow.py
hic/initial.py
hic.egg-info/PKG-INFO
hic.egg-info/SOURCES.txt
hic.egg-info/dependency_links.txt
hic.egg-info/requires.txt
hic.egg-info/top_level.txt
hic/test/__init__.py
hic/test/test_flow.py
hic/test/test_initial.py